prettynum/__init__.py
prettynum/prettynum.py
prettynum-0.1.0.dist-info/LICENSE
prettynum-0.1.0.dist-info/WHEEL
prettynum-0.1.0.dist-info/METADATA
prettynum-0.1.0.dist-info/RECORD
