Metadata-Version: 2.1
Name: prettynum
Version: 0.1.0
Summary: Simple number formatting for python
Home-page: https://github.com/SamEdwardes/prettynum
License: MIT
Keywords: python,formatting
Author: SamEdwardes
Author-email: edwardes.s@gmail.com
Requires-Python: >=3.5,<4.0
Classifier: License :: OSI Approved :: MIT License
Classifier: Programming Language :: Python :: 3
Classifier: Programming Language :: Python :: 3.5
Classifier: Programming Language :: Python :: 3.6
Classifier: Programming Language :: Python :: 3.7
Classifier: Programming Language :: Python :: 3.8
Classifier: Programming Language :: Python :: 3.9
Project-URL: Repository, https://github.com/SamEdwardes/prettynum
